bleak_retry_connector/__init__.py
bleak_retry_connector/bleak_manager.py
bleak_retry_connector/bluez.py
bleak_retry_connector/const.py
bleak_retry_connector/dbus.py
bleak_retry_connector/py.typed
bleak_retry_connector/util.py
bleak_retry_connector-4.4.3.dist-info/LICENSE
bleak_retry_connector-4.4.3.dist-info/METADATA
bleak_retry_connector-4.4.3.dist-info/WHEEL
bleak_retry_connector-4.4.3.dist-info/RECORD
