Metadata-Version: 2.3
Name: bleak-retry-connector
Version: 4.4.3
Summary: A connector for Bleak Clients that handles transient connection failures
License: MIT
Author: J. Nick Koston
Author-email: nick@koston.org
Requires-Python: >=3.10
Classifier: Development Status :: 2 - Pre-Alpha
Classifier: Intended Audience :: Developers
Classifier: License :: OSI Approved :: MIT License
Classifier: Natural Language :: English
Classifier: Operating System :: OS Independent
Classifier: Programming Language :: Python :: 3
Classifier: Programming Language :: Python :: 3.10
Classifier: Programming Language :: Python :: 3.11
Classifier: Programming Language :: Python :: 3.12
Classifier: Programming Language :: Python :: 3.13
Classifier: Topic :: Software Development :: Libraries
Requires-Dist: async-timeout (>=3.0.0) ; python_version < "3.11"
Requires-Dist: bleak (>=1) ; python_version >= "3.10" and python_version < "3.14"
Requires-Dist: bluetooth-adapters (>=0.15.2) ; python_version >= "3.10" and python_version < "3.14" and platform_system == "Linux"
Requires-Dist: dbus-fast (>=1.14.0) ; platform_system == "Linux"
Project-URL: Bug Tracker, https://github.com/bluetooth-devices/bleak-retry-connector/issues
Project-URL: Changelog, https://github.com/bluetooth-devices/bleak-retry-connector/blob/main/CHANGELOG.md
Project-URL: Documentation, https://bleak-retry-connector.readthedocs.io
Project-URL: Repository, https://github.com/bluetooth-devices/bleak-retry-connector
